libmineshaft/__init__.py
libmineshaft/__main__.py
libmineshaft/blocks.py
libmineshaft/classes.py
libmineshaft/colors.py
libmineshaft/constants.py
libmineshaft/items.py
libmineshaft/lang.py
libmineshaft/layers.py
libmineshaft/main.py
libmineshaft/music.py
libmineshaft/shell.py
libmineshaft/themes.py
libmineshaft/world.py
libmineshaft-0.1.6.dist-info/LICENSE
libmineshaft-0.1.6.dist-info/METADATA
libmineshaft-0.1.6.dist-info/WHEEL
libmineshaft-0.1.6.dist-info/entry_points.txt
libmineshaft-0.1.6.dist-info/top_level.txt
libmineshaft-0.1.6.dist-info/RECORD
