Metadata-Version: 2.1
Name: libmineshaft
Version: 0.1.6
Summary: Helper library for Mineshaft and mod creation for it
Home-page: http://mineshaft.ml
Author: Double Fractal Game Studios
Author-email: mayu2kura1@gmail.com
Maintainer: Alexey Pavlov
Maintainer-email: pezleha@gmail.om
License: UNKNOWN
Download-URL: http://github.com/Mineshaft-game/libmineshaft
Keywords: Minecraft,Mineshaft,Pygame,Minecraft clone,2D,Minecraft 2D,Mineshaft 2D,Minecraft remake,libmineshaft,Minecraft mod,mod
Platform: UNKNOWN
Classifier: License :: OSI Approved :: GNU Lesser General Public License v2 or later (LGPLv2+)
Classifier: Environment :: Console
Classifier: Intended Audience :: Developers
Classifier: Natural Language :: English
Classifier: Operating System :: MacOS
Classifier: Operating System :: MacOS :: MacOS 9
Classifier: Operating System :: MacOS :: MacOS X
Classifier: Operating System :: Microsoft :: Windows
Classifier: Operating System :: Microsoft :: Windows :: Windows 10
Classifier: Operating System :: Microsoft :: Windows :: Windows 7
Classifier: Operating System :: Microsoft :: Windows :: Windows 8
Classifier: Operating System :: Microsoft :: Windows :: Windows 8.1
Classifier: Operating System :: OS Independent
Classifier: Operating System :: POSIX
Classifier: Operating System :: POSIX :: Linux
Classifier: Operating System :: Unix
Classifier: Programming Language :: Other
Classifier: Programming Language :: Other Scripting Engines
Classifier: Programming Language :: Python
Classifier: Programming Language :: Python :: 3
Classifier: Programming Language :: Python :: 3 :: Only
Classifier: Programming Language :: Python :: 3.7
Classifier: Programming Language :: Python :: 3.8
Classifier: Topic :: Games/Entertainment
Classifier: Topic :: Games/Entertainment :: Simulation
Classifier: Topic :: Software Development :: Build Tools
Classifier: Topic :: Software Development :: Interpreters
Classifier: Topic :: Software Development :: Libraries :: pygame
Classifier: Topic :: System :: Shells
Classifier: Topic :: System :: Software Distribution
Requires-Dist: py-cui
Requires-Dist: pygame-menu
Requires-Dist: pygame (>=2.0.1)
Requires-Dist: storyscript (>=0.0.3)
